flask_debug_api
