Metadata-Version: 1.1
Name: Flask-Debug-API
Version: 0.1.0
Summary: API Browser for Flask-DebugToolbar
Home-page: http://github.com/kevinbeaty/flask-debug-api
Author: Kevin Beaty
Author-email: kevin@simplectic.com
License: MIT
Platform: any
Classifier: Development Status :: 4 - Beta
Classifier: Environment :: Web Environment
Classifier: Intended Audience :: Developers
Classifier: License :: OSI Approved :: MIT License
Classifier: Topic :: Internet :: WWW/HTTP :: Dynamic Content
Classifier: Topic :: Software Development :: Libraries :: Python Modules
